tup/__init__.py
tup/cli.py
tup/client.py
tup/config.py
tup/core.py
tup/packager.py
tup/runner.py
tup/types.py
tup_cli-0.1.0.dist-info/METADATA
tup_cli-0.1.0.dist-info/WHEEL
tup_cli-0.1.0.dist-info/entry_points.txt
tup_cli-0.1.0.dist-info/RECORD
