Metadata-Version: 2.4
Name: tup-cli
Version: 0.1.0
Summary: Run any command in the cloud. Close your laptop, keep running.
Project-URL: Homepage, https://github.com/sdan/tup
Project-URL: Documentation, https://github.com/sdan/tup#readme
Project-URL: Repository, https://github.com/sdan/tup
Project-URL: Issues, https://github.com/sdan/tup/issues
Author: sdan
License-Expression: MIT
Keywords: cloud,cloudflare,containers,distributed,ml,serverless,training
Classifier: Development Status :: 3 - Alpha
Classifier: Intended Audience :: Developers
Classifier: Intended Audience :: Science/Research
Classifier: License :: OSI Approved :: MIT License
Classifier: Operating System :: OS Independent
Classifier: Programming Language :: Python :: 3
Classifier: Programming Language :: Python :: 3.10
Classifier: Programming Language :: Python :: 3.11
Classifier: Programming Language :: Python :: 3.12
Classifier: Topic :: Scientific/Engineering :: Artificial Intelligence
Classifier: Topic :: System :: Distributed Computing
Requires-Python: >=3.10
Requires-Dist: click>=8.0
Requires-Dist: cloudpickle>=3.0
Requires-Dist: httpx>=0.25
Requires-Dist: pydantic>=2.0
Requires-Dist: termcolor>=2.0
Requires-Dist: tomli>=2.0; python_version < '3.11'
Provides-Extra: dev
Requires-Dist: mypy>=1.0; extra == 'dev'
Requires-Dist: pytest-asyncio>=0.21; extra == 'dev'
Requires-Dist: pytest>=7.0; extra == 'dev'
Requires-Dist: ruff>=0.1; extra == 'dev'
